{
  "generatedAt": "2025-12-20T23:27:58.756Z",
  "isDryRun": false,
  "results": {
    "filesProcessed": [
      {
        "file": "app\\features\\landing\\landing.component.html",
        "changes": 4
      },
      {
        "file": "app\\features\\portal\\face-recognition-demo\\face-recognition-demo.component.html",
        "changes": 1
      },
      {
        "file": "app\\features\\portal\\face-recognition-live\\face-recognition-live.component.html",
        "changes": 1
      },
      {
        "file": "app\\features\\portal\\hr-dashboard\\hr-dashboard.component.html",
        "changes": 1
      },
      {
        "file": "app\\features\\portal\\mfa-setup\\mfa-setup.component.html",
        "changes": 1
      },
      {
        "file": "app\\features\\portal\\mobile-demo\\mobile-demo.component.html",
        "changes": 1
      },
      {
        "file": "app\\features\\portal\\rating-demo\\rating-demo.component.html",
        "changes": 2
      },
      {
        "file": "app\\features\\portal\\validation-demo\\validation-demo.component.html",
        "changes": 1
      },
      {
        "file": "app\\features\\public\\event-registration\\event-registration.component.html",
        "changes": 1
      },
      {
        "file": "app\\features\\super-admin\\companies\\companies.component.html",
        "changes": 1
      },
      {
        "file": "app\\shared\\components\\face-recognition\\face-recognition.component.html",
        "changes": 2
      },
      {
        "file": "app\\shared\\components\\gallery\\gallery.component.html",
        "changes": 2
      },
      {
        "file": "app\\shared\\components\\group-face-recognition\\group-face-recognition.component.html",
        "changes": 2
      },
      {
        "file": "app\\shared\\components\\lock-screen\\lock-screen.component.html",
        "changes": 1
      },
      {
        "file": "app\\shared\\components\\mobile-camera\\mobile-camera.component.html",
        "changes": 1
      },
      {
        "file": "app\\shared\\components\\swiper-gallery\\swiper-gallery.component.html",
        "changes": 2
      },
      {
        "file": "app\\shared\\components\\timestamp\\timestamp.component.html",
        "changes": 1
      }
    ],
    "tagsFound": 25,
    "tagsOptimized": 25,
    "tagsNeedingOptimization": [
      {
        "file": "app\\features\\landing\\landing.component.html",
        "tag": "<img [src]=\"slide.image\" [alt]=\"slide.title\" class=\"slider-image\">"
      },
      {
        "file": "app\\features\\landing\\landing.component.html",
        "tag": "<img [src]=\"feature.image || '/assets/images/placeholder.jpg'\" \r\n                 [alt]=\"feature.tit"
      },
      {
        "file": "app\\features\\landing\\landing.component.html",
        "tag": "<img [src]=\"image.url\" [alt]=\"image.title\" class=\"gallery-image\">"
      },
      {
        "file": "app\\features\\landing\\landing.component.html",
        "tag": "<img [src]=\"image.thumbnail || image.url\" [alt]=\"image.title\">"
      },
      {
        "file": "app\\features\\portal\\face-recognition-demo\\face-recognition-demo.component.html",
        "tag": "<img [src]=\"activity.snapshot\" alt=\"Face Snapshot\" class=\"w-12 h-12 rounded-full object-cover border"
      },
      {
        "file": "app\\features\\portal\\face-recognition-live\\face-recognition-live.component.html",
        "tag": "<img [src]=\"face.image\" alt=\"Detected Face\" />"
      },
      {
        "file": "app\\features\\portal\\hr-dashboard\\hr-dashboard.component.html",
        "tag": "<img *ngIf=\"employee.avatar\" [src]=\"employee.avatar\" [alt]=\"employee.firstName\">"
      },
      {
        "file": "app\\features\\portal\\mfa-setup\\mfa-setup.component.html",
        "tag": "<img [src]=\"mfaSetup()?.qrCode\" alt=\"MFA QR Code\" class=\"w-48 h-48\">"
      },
      {
        "file": "app\\features\\portal\\mobile-demo\\mobile-demo.component.html",
        "tag": "<img [src]=\"lastPhoto.dataUrl\" [alt]=\"'Last photo'\" class=\"photo-preview\">"
      },
      {
        "file": "app\\features\\portal\\rating-demo\\rating-demo.component.html",
        "tag": "<img [src]=\"product.image\" [alt]=\"product.name\" class=\"w-full h-48 object-cover rounded-lg\">"
      },
      {
        "file": "app\\features\\portal\\rating-demo\\rating-demo.component.html",
        "tag": "<img [src]=\"review.userAvatar\" [alt]=\"review.userName\" class=\"w-10 h-10 rounded-full\">"
      },
      {
        "file": "app\\features\\portal\\validation-demo\\validation-demo.component.html",
        "tag": "<img [src]=\"filePreview()\" alt=\"Preview\" class=\"w-20 h-20 object-cover rounded\">"
      },
      {
        "file": "app\\features\\public\\event-registration\\event-registration.component.html",
        "tag": "<img [src]=\"faceImagePreview()\" alt=\"Face preview\" class=\"w-32 h-32 object-cover rounded-lg border-2"
      },
      {
        "file": "app\\features\\super-admin\\companies\\companies.component.html",
        "tag": "<img *ngIf=\"formData.picture\" [src]=\"getImageUrl(formData.picture)\" alt=\"Company Logo\" class=\"w-full"
      },
      {
        "file": "app\\shared\\components\\face-recognition\\face-recognition.component.html",
        "tag": "<img [src]=\"previewImage\" alt=\"Preview\" class=\"preview-image\">"
      },
      {
        "file": "app\\shared\\components\\face-recognition\\face-recognition.component.html",
        "tag": "<img [src]=\"face.imageData\" [alt]=\"face.name\" class=\"face-image\">"
      },
      {
        "file": "app\\shared\\components\\gallery\\gallery.component.html",
        "tag": "<img\r\n          [src]=\"item.thumbnail || item.src\"\r\n          [alt]=\"item.alt || item.title\"\r\n      "
      },
      {
        "file": "app\\shared\\components\\gallery\\gallery.component.html",
        "tag": "<img\r\n          [src]=\"lightboxItem.fullSize || lightboxItem.src\"\r\n          [alt]=\"lightboxItem.alt"
      },
      {
        "file": "app\\shared\\components\\group-face-recognition\\group-face-recognition.component.html",
        "tag": "<img [src]=\"face.snapshot\" alt=\"Face Snapshot\" class=\"snapshot-img\">"
      },
      {
        "file": "app\\shared\\components\\group-face-recognition\\group-face-recognition.component.html",
        "tag": "<img *ngIf=\"recognition.snapshot\" [src]=\"recognition.snapshot\" class=\"mini-snapshot\" alt=\"face\">"
      },
      {
        "file": "app\\shared\\components\\lock-screen\\lock-screen.component.html",
        "tag": "<img *ngIf=\"userInfo.avatar\" [src]=\"userInfo.avatar\" [alt]=\"userInfo.name\" class=\"avatar-image\">"
      },
      {
        "file": "app\\shared\\components\\mobile-camera\\mobile-camera.component.html",
        "tag": "<img [src]=\"lastPhoto.dataUrl\" [alt]=\"'Captured photo'\" class=\"preview-image\">"
      },
      {
        "file": "app\\shared\\components\\swiper-gallery\\swiper-gallery.component.html",
        "tag": "<img\r\n            [src]=\"slide.src\"\r\n            [alt]=\"slide.alt\"\r\n            class=\"slide-image\"\r"
      },
      {
        "file": "app\\shared\\components\\swiper-gallery\\swiper-gallery.component.html",
        "tag": "<img\r\n            [src]=\"slide.thumbnail || slide.src\"\r\n            [alt]=\"slide.alt\"\r\n            c"
      },
      {
        "file": "app\\shared\\components\\timestamp\\timestamp.component.html",
        "tag": "<img [src]=\"previewImage\" alt=\"Preview\" class=\"preview-image\">"
      }
    ],
    "changes": [
      {
        "file": "app\\features\\landing\\landing.component.html",
        "changes": [
          {
            "original": "<img [src]=\"slide.image\" [alt]=\"slide.title\" class=\"slider-image\">",
            "optimized": "<img appImageOptimization [ngSrc]=\"slide.image\" [alt]=\"slide.title\" class=\"slide"
          },
          {
            "original": "<img [src]=\"feature.image || '/assets/images/placeholder.jpg'\" \r\n               ",
            "optimized": "<img appImageOptimization [ngSrc]=\"feature.image || \"/assets/images/placeholder."
          },
          {
            "original": "<img [src]=\"image.url\" [alt]=\"image.title\" class=\"gallery-image\">",
            "optimized": "<img appImageOptimization [ngSrc]=\"image.url\" [alt]=\"image.title\" class=\"gallery"
          },
          {
            "original": "<img [src]=\"image.thumbnail || image.url\" [alt]=\"image.title\">",
            "optimized": "<img appImageOptimization [ngSrc]=\"image.thumbnail || image.url\" [alt]=\"image.ti"
          }
        ]
      },
      {
        "file": "app\\features\\portal\\face-recognition-demo\\face-recognition-demo.component.html",
        "changes": [
          {
            "original": "<img [src]=\"activity.snapshot\" alt=\"Face Snapshot\" class=\"w-12 h-12 rounded-full",
            "optimized": "<img appImageOptimization [ngSrc]=\"activity.snapshot\" alt=\"Face Snapshot\" class="
          }
        ]
      },
      {
        "file": "app\\features\\portal\\face-recognition-live\\face-recognition-live.component.html",
        "changes": [
          {
            "original": "<img [src]=\"face.image\" alt=\"Detected Face\" />",
            "optimized": "<img appImageOptimization [ngSrc]=\"face.image\" alt=\"Detected Face\" loading=\"lazy"
          }
        ]
      },
      {
        "file": "app\\features\\portal\\hr-dashboard\\hr-dashboard.component.html",
        "changes": [
          {
            "original": "<img *ngIf=\"employee.avatar\" [src]=\"employee.avatar\" [alt]=\"employee.firstName\">",
            "optimized": "<img appImageOptimization *ngIf=\"employee.avatar\" [ngSrc]=\"employee.avatar\" [alt"
          }
        ]
      },
      {
        "file": "app\\features\\portal\\mfa-setup\\mfa-setup.component.html",
        "changes": [
          {
            "original": "<img [src]=\"mfaSetup()?.qrCode\" alt=\"MFA QR Code\" class=\"w-48 h-48\">",
            "optimized": "<img appImageOptimization [ngSrc]=\"mfaSetup()?.qrCode\" alt=\"MFA QR Code\" class=\""
          }
        ]
      },
      {
        "file": "app\\features\\portal\\mobile-demo\\mobile-demo.component.html",
        "changes": [
          {
            "original": "<img [src]=\"lastPhoto.dataUrl\" [alt]=\"'Last photo'\" class=\"photo-preview\">",
            "optimized": "<img appImageOptimization [ngSrc]=\"lastPhoto.dataUrl\" [alt]=\"'Last photo'\" class"
          }
        ]
      },
      {
        "file": "app\\features\\portal\\rating-demo\\rating-demo.component.html",
        "changes": [
          {
            "original": "<img [src]=\"product.image\" [alt]=\"product.name\" class=\"w-full h-48 object-cover ",
            "optimized": "<img appImageOptimization [ngSrc]=\"product.image\" [alt]=\"product.name\" class=\"w-"
          },
          {
            "original": "<img [src]=\"review.userAvatar\" [alt]=\"review.userName\" class=\"w-10 h-10 rounded-",
            "optimized": "<img appImageOptimization [ngSrc]=\"review.userAvatar\" [alt]=\"review.userName\" cl"
          }
        ]
      },
      {
        "file": "app\\features\\portal\\validation-demo\\validation-demo.component.html",
        "changes": [
          {
            "original": "<img [src]=\"filePreview()\" alt=\"Preview\" class=\"w-20 h-20 object-cover rounded\">",
            "optimized": "<img appImageOptimization [ngSrc]=\"filePreview()\" alt=\"Preview\" class=\"w-20 h-20"
          }
        ]
      },
      {
        "file": "app\\features\\public\\event-registration\\event-registration.component.html",
        "changes": [
          {
            "original": "<img [src]=\"faceImagePreview()\" alt=\"Face preview\" class=\"w-32 h-32 object-cover",
            "optimized": "<img appImageOptimization [ngSrc]=\"faceImagePreview()\" alt=\"Face preview\" class="
          }
        ]
      },
      {
        "file": "app\\features\\super-admin\\companies\\companies.component.html",
        "changes": [
          {
            "original": "<img *ngIf=\"formData.picture\" [src]=\"getImageUrl(formData.picture)\" alt=\"Company",
            "optimized": "<img appImageOptimization *ngIf=\"formData.picture\" [ngSrc]=\"getImageUrl(formData"
          }
        ]
      },
      {
        "file": "app\\shared\\components\\face-recognition\\face-recognition.component.html",
        "changes": [
          {
            "original": "<img [src]=\"previewImage\" alt=\"Preview\" class=\"preview-image\">",
            "optimized": "<img appImageOptimization [ngSrc]=\"previewImage\" alt=\"Preview\" class=\"preview-im"
          },
          {
            "original": "<img [src]=\"face.imageData\" [alt]=\"face.name\" class=\"face-image\">",
            "optimized": "<img appImageOptimization [ngSrc]=\"face.imageData\" [alt]=\"face.name\" class=\"face"
          }
        ]
      },
      {
        "file": "app\\shared\\components\\gallery\\gallery.component.html",
        "changes": [
          {
            "original": "<img\r\n          [src]=\"item.thumbnail || item.src\"\r\n          [alt]=\"item.alt ||",
            "optimized": "<img appImageOptimization\r\n          [ngSrc]=\"item.thumbnail || item.src\"\r\n     "
          },
          {
            "original": "<img\r\n          [src]=\"lightboxItem.fullSize || lightboxItem.src\"\r\n          [al",
            "optimized": "<img appImageOptimization\r\n          [ngSrc]=\"lightboxItem.fullSize || lightboxI"
          }
        ]
      },
      {
        "file": "app\\shared\\components\\group-face-recognition\\group-face-recognition.component.html",
        "changes": [
          {
            "original": "<img [src]=\"face.snapshot\" alt=\"Face Snapshot\" class=\"snapshot-img\">",
            "optimized": "<img appImageOptimization [ngSrc]=\"face.snapshot\" alt=\"Face Snapshot\" class=\"sna"
          },
          {
            "original": "<img *ngIf=\"recognition.snapshot\" [src]=\"recognition.snapshot\" class=\"mini-snaps",
            "optimized": "<img appImageOptimization *ngIf=\"recognition.snapshot\" [ngSrc]=\"recognition.snap"
          }
        ]
      },
      {
        "file": "app\\shared\\components\\lock-screen\\lock-screen.component.html",
        "changes": [
          {
            "original": "<img *ngIf=\"userInfo.avatar\" [src]=\"userInfo.avatar\" [alt]=\"userInfo.name\" class",
            "optimized": "<img appImageOptimization *ngIf=\"userInfo.avatar\" [ngSrc]=\"userInfo.avatar\" [alt"
          }
        ]
      },
      {
        "file": "app\\shared\\components\\mobile-camera\\mobile-camera.component.html",
        "changes": [
          {
            "original": "<img [src]=\"lastPhoto.dataUrl\" [alt]=\"'Captured photo'\" class=\"preview-image\">",
            "optimized": "<img appImageOptimization [ngSrc]=\"lastPhoto.dataUrl\" [alt]=\"'Captured photo'\" c"
          }
        ]
      },
      {
        "file": "app\\shared\\components\\swiper-gallery\\swiper-gallery.component.html",
        "changes": [
          {
            "original": "<img\r\n            [src]=\"slide.src\"\r\n            [alt]=\"slide.alt\"\r\n            ",
            "optimized": "<img appImageOptimization\r\n            [ngSrc]=\"slide.src\"\r\n            [alt]=\"s"
          },
          {
            "original": "<img\r\n            [src]=\"slide.thumbnail || slide.src\"\r\n            [alt]=\"slide",
            "optimized": "<img appImageOptimization\r\n            [ngSrc]=\"slide.thumbnail || slide.src\"\r\n "
          }
        ]
      },
      {
        "file": "app\\shared\\components\\timestamp\\timestamp.component.html",
        "changes": [
          {
            "original": "<img [src]=\"previewImage\" alt=\"Preview\" class=\"preview-image\">",
            "optimized": "<img appImageOptimization [ngSrc]=\"previewImage\" alt=\"Preview\" class=\"preview-im"
          }
        ]
      }
    ]
  }
}